{"id":"pxnxB8uLw","title":"Cross-zone team sync  Testing","meetingDateISO":"2026-06-28T12:30:00.000Z","refTz":"Europe/Berlin","weekday":2,"duration":60,"zones":[{"id":"z_cest","label":"CEST · Europe","tz":"Europe/Berlin","ws":480,"we":1080},{"id":"z_aest","label":"AEST · Proxmed (Melbourne)","tz":"Australia/Melbourne","ws":480,"we":1230},{"id":"z_ist","label":"IST · You (Delhi)","tz":"Asia/Kolkata","ws":540,"we":1140}],"roster":[{"rosterId":"r1","name":"Adelheid Orend","zoneId":"z_cest","tokenHash":"572f30a4204a77d7a24eee8d273e184601acd3714961333c956ec624e197039c"},{"rosterId":"r2","name":"Zita Mehesz","zoneId":"z_cest","tokenHash":"91aaa2cc49e1966f7378fa10411eb0256b62ec3ff9cb9d0b33f7d878f7ff7d7b"},{"rosterId":"r3","name":"Doris Zimmermann","zoneId":"z_cest","tokenHash":"c5f92c943aa330e9a3b019e4d39333bb890fa201165effcbdc7683d73c034804"},{"rosterId":"r4","name":"Gagan Sharma","zoneId":"z_aest","tokenHash":"0527fb5fd9c2bae92c45fbce41d8b7849e96a5573846ac1b1771d2a4a65ee28f"},{"rosterId":"r5","name":"Niruta Dhimal","zoneId":"z_aest","tokenHash":"dd3f108194f4b8a54c6b9e63b0bb84799c54f3c9c42b69498b8d14e4983acdd5"},{"rosterId":"r6","name":"Aditya Chaturvedi","zoneId":"z_ist","tokenHash":"4ba5f1253c60d2c38dc26e1a8109d0cff75a104553f916ec12d59738feaf5f2b"}],"slots":[{"id":"s_3uz2x4x","utc":"2026-06-28T12:30:00.000Z","label":""}]}